pls/__init__.py
pls/config/__init__.py
pls/config/constants.py
pls/config/files.py
pls/config/icons.py
pls/config/prefs.py
pls/config/specs.py
pls/data/__init__.py
pls/data/constants.yml
pls/data/emoji_icons.yml
pls/data/nerd_icons.yml
pls/data/node_specs.yml
pls/data/prefs.yml
pls/data/schema/pls_config.yml
pls/data/solarized.yml
pls/data/utils.py
pls/enums/__init__.py
pls/enums/base.py
pls/enums/icon_type.py
pls/enums/node_type.py
pls/enums/unit_system.py
pls/exceptions.py
pls/fs/__init__.py
pls/fs/git.py
pls/fs/list.py
pls/fs/stats.py
pls/globals/__init__.py
pls/globals/args.py
pls/globals/console.py
pls/globals/state.py
pls/log/__init__.py
pls/log/config.py
pls/main.py
pls/models/__init__.py
pls/models/column_spec.py
pls/models/composables/__init__.py
pls/models/composables/children.py
pls/models/composables/collapse.py
pls/models/composables/git.py
pls/models/composables/imp.py
pls/models/composables/name.py
pls/models/composables/spec.py
pls/models/composables/stat.py
pls/models/composables/type.py
pls/models/format_rules.py
pls/models/node.py
pls/models/node_spec.py
pls/models/tree.py
pls/output/__init__.py
pls/output/columns/__init__.py
pls/output/columns/all_columns.py
pls/output/columns/detail_columns.py
pls/output/columns_printer.py
pls/output/printers.py
pls/output/solarized.py
pls/output/table_printer.py
pls/output/update.py
pls/parser/__init__.py
pls/parser/actions.py
pls/parser/args/__init__.py
pls/parser/args/dev.py
pls/parser/args/filter.py
pls/parser/args/info.py
pls/parser/args/meta.py
pls/parser/args/pos.py
pls/parser/args/pres.py
pls/parser/args/sort.py
pls/parser/base.py
pls/parser/parser.py
pls/parser/validation.py
pls/utils/__init__.py
pls/utils/strip_fmt.py
pls-6.0.0.dist-info/LICENSE
pls-6.0.0.dist-info/METADATA
pls-6.0.0.dist-info/WHEEL
pls-6.0.0.dist-info/entry_points.txt
pls-6.0.0.dist-info/RECORD
