Metadata-Version: 2.1
Name: pls
Version: 6.0.0
Summary: `pls` is a prettier and powerful `ls` for the pros.
Home-page: https://dhruvkb.github.io/pls
License: GPL-3.0-or-later
Author: Dhruv Bhanushali
Requires-Python: >=3.8,<4.0
Classifier: License :: OSI Approved :: GNU General Public License v3 or later (GPLv3+)
Classifier: Programming Language :: Python :: 3
Classifier: Programming Language :: Python :: 3.8
Classifier: Programming Language :: Python :: 3.9
Classifier: Programming Language :: Python :: 3.10
Classifier: Programming Language :: Python :: 3.11
Requires-Dist: PyYAML (>=6.0,<7.0)
Requires-Dist: requests (>=2.27.1,<3.0.0)
Requires-Dist: rich (>=12.5.1,<13.0.0)
Project-URL: Documentation, https://dhruvkb.github.io/pls
Project-URL: Repository, https://github.com/dhruvkb/pls
